flask_graylog.py
Flask_Graylog-1.1.2.dist-info/DESCRIPTION.rst
Flask_Graylog-1.1.2.dist-info/METADATA
Flask_Graylog-1.1.2.dist-info/RECORD
Flask_Graylog-1.1.2.dist-info/WHEEL
Flask_Graylog-1.1.2.dist-info/metadata.json
Flask_Graylog-1.1.2.dist-info/top_level.txt
