Metadata-Version: 2.0
Name: Flask-Graylog
Version: 1.1.2
Summary: Configure Graylog logging handlers and middleware for your Flask app
Home-page: https://github.com/underdogio/flask-graylog.git
Author: Brett Langdon
Author-email: me@brett.is
License: MIT
Platform: any
Classifier: Environment :: Web Environment
Classifier: Intended Audience :: Developers
Classifier: License :: OSI Approved :: MIT License
Classifier: Operating System :: OS Independent
Classifier: Programming Language :: Python
Classifier: Topic :: Software Development :: Libraries :: Python Modules
Requires-Dist: Flask
Requires-Dist: graypy
